kw6/__init__.py
kw6/camera.py
kw6/header.py
kw6/position.py
kw6/reader.py
kw6/settings.py
kw6/types.py
kw6-1.0.1.dist-info/LICENSE
kw6-1.0.1.dist-info/METADATA
kw6-1.0.1.dist-info/WHEEL
kw6-1.0.1.dist-info/RECORD
