Metadata-Version: 2.1
Name: kw6
Version: 1.0.1
Summary: Minimalistic library for reading files in the kw6 file format
License: Apache 2.0
Author: NextML AB
Requires-Python: >=3.8,<3.11
Classifier: License :: Other/Proprietary License
Classifier: Programming Language :: Python :: 3
Classifier: Programming Language :: Python :: 3.8
Classifier: Programming Language :: Python :: 3.9
Classifier: Programming Language :: Python :: 3.10
Requires-Dist: Pillow (>=9.0.0,<10.0.0)
Requires-Dist: numpy (>=1.21.2,<2.0.0)
Requires-Dist: pydantic (>=2.0.0,<3.0.0)
